aptos_brownie.py
aptos_brownie-3.0.6.dist-info/METADATA
aptos_brownie-3.0.6.dist-info/WHEEL
aptos_brownie-3.0.6.dist-info/top_level.txt
aptos_brownie-3.0.6.dist-info/RECORD
