Metadata-Version: 2.1
Name: aptos-brownie
Version: 3.0.6
Summary: Aptos Package Tool
Home-page: https://github.com/OmniBTC/OmniSwap/blob/main/utils
Author: DaiWei
Author-email: dw1253464613@gmail.com
License: MIT
Classifier: Development Status :: 4 - Beta
Classifier: Intended Audience :: Developers
Classifier: Topic :: System :: Logging
Classifier: License :: OSI Approved :: MIT License
Classifier: Programming Language :: Python :: 3
Classifier: Programming Language :: Python :: 3.3
Classifier: Programming Language :: Python :: 3.4
Classifier: Programming Language :: Python :: 3.5
Classifier: Programming Language :: Python :: 3.6
Classifier: Programming Language :: Python :: 3.7
Classifier: Programming Language :: Python :: 3.8
Requires-Python: >=3.6
Requires-Dist: aptos-sdk
Requires-Dist: pyyaml
Requires-Dist: toml
